hoops_dynasty_api/__init__.py
hoops_dynasty_api/bin/__init__.py
hoops_dynasty_api/bin/cli_v2.py
hoops_dynasty_api/classes/__init__.py
hoops_dynasty_api/classes/player.py
hoops_dynasty_api/classes/recruit.py
hoops_dynasty_api/classes/team.py
hoops_dynasty_api/classes/common_funcs/__init__.py
hoops_dynasty_api/classes/common_funcs/funcs.py
hoops_dynasty_api/exceptions/__init__.py
hoops_dynasty_api/exceptions/file_handling_exceptions.py
hoops_dynasty_api/exceptions/web_exceptions.py
hoops_dynasty_api/extract_data/__init__.py
hoops_dynasty_api/extract_data/cli_orch.py
hoops_dynasty_api/extract_data/process_data.py
hoops_dynasty_api/loaders/__init__.py
hoops_dynasty_api/loaders/bigquery.py
hoops_dynasty_api/web/__init__.py
hoops_dynasty_api/web/browser.py
hoops_dynasty_api-0.5.4.dist-info/LICENSE
hoops_dynasty_api-0.5.4.dist-info/METADATA
hoops_dynasty_api-0.5.4.dist-info/WHEEL
hoops_dynasty_api-0.5.4.dist-info/entry_points.txt
hoops_dynasty_api-0.5.4.dist-info/top_level.txt
hoops_dynasty_api-0.5.4.dist-info/RECORD
