Metadata-Version: 2.1
Name: hoops-dynasty-api
Version: 0.5.4
Summary: connects to hoops dynasty in whatifsports and pulls data
Home-page: https://gitlab.com/whatifsports-data-integration/packages/hoops-dynasty-api
License: MIT
Project-URL: Repository, https://gitlab.com/zachstocker/hoops-dynasty-api
Classifier: Development Status :: 4 - Beta
Classifier: Operating System :: OS Independent
Classifier: License :: OSI Approved :: MIT License
Classifier: Programming Language :: Python :: 3.11
Requires-Python: >=3.11
License-File: /builds/whatifsports-data-integration/packages/hoops-dynasty-api/LICENSE
Requires-Dist: selenium==4.21.0
Requires-Dist: beautifulsoup4==4.9.3
Requires-Dist: pandas==2.2.2
Requires-Dist: openpyxl==3.0.7
Requires-Dist: click==8.1.7
Requires-Dist: pypandoc==1.13
Requires-Dist: undetected-chromedriver==3.5.5
Requires-Dist: xlsxwriter==3.2.0
Requires-Dist: numpy<2.0
Requires-Dist: pyarrow==14.0.1
Requires-Dist: google-cloud-bigquery==3.11.4
Requires-Dist: pandas-gbq==0.23.1
